client/__init__.py
env/__init__.py
env/env.py
env/preset.py
env/then.py
env/urls.py
env/when.py
scenarios/__init__.py
scenarios/client_create_project.py
scenarios/dataset_description.py
scenarios/dataset_location_id.py
scenarios/dataset_location_uri.py
scenarios/dataset_project_link.py
scenarios/dataset_storage_size.py
scenarios/dataset_update_timestamp.py
scenarios/list_datasets.py
scenarios/list_projects.py
scenarios/menu_stats.py
scenarios/project_stats.py
scenarios/search_datasets.py
scenarios/stale_status.py
scenarios/view_dataset.py
scenarios/view_project.py
mlp_client-0.0.1.dist-info/METADATA
mlp_client-0.0.1.dist-info/WHEEL
mlp_client-0.0.1.dist-info/top_level.txt
mlp_client-0.0.1.dist-info/RECORD
