Metadata-Version: 2.1
Name: mlp-client
Version: 0.0.1
Summary: Python client for ML Pipelines
Home-page: https://github.com/bitgn/ml-pipelines
Author: Example Author
Author-email: rinat@abdullin.com
License: UNKNOWN
Platform: UNKNOWN
Classifier: Programming Language :: Python :: 3
Classifier: License :: OSI Approved :: MIT License
Classifier: Operating System :: OS Independent
